{                                                                                                                                     
        "clientID": "SxQuiT0h4guwVsGjgM4JoA==",                                                                                       
        "serverToken": "1@F7y+kLveNfr3+3k3fB4Dop0611+jv/rd1vDZhf6AG3F4agx9zVw3NIL9PE5aSHDs04+DBWfugGystQ==",                          
        "clientToken": "odkxnWS+EyDjUMH44toB99kK+np7+3Oj52NX21TfK6I=",                                                                
        "encKey": "aVuRQRF2RRhJuTAPd4Wj/JAuVzLLkEXTKgjFcaen1Mk=",                                                                     
        "macKey": "mk8mFRrSgrgcvRFOOo69cEuiA+wNSey9iUljdQ+pZlw="                                                                      
}   
